desktop.ini
elpigraph/_AlterStructure.py
elpigraph/_BaseElPiWrapper.py
elpigraph/_EMAdjustment.py
elpigraph/__init__.py
elpigraph/_graph_editing.py
elpigraph/_topologies.py
elpigraph/_version.py
elpigraph/desktop.ini
elpigraph/plot.py
elpigraph/utils.py
elpigraph/src/BaseElPi.py
elpigraph/src/PCA.py
elpigraph/src/__init__.py
elpigraph/src/core.py
elpigraph/src/desktop.ini
elpigraph/src/distutils.py
elpigraph/src/grammar_operations.py
elpigraph/src/graphs.py
elpigraph/src/reporting.py
elpigraph/src/supervised.py
elpigraph/src/synthetic.py
elpigraph_python-0.3.2.dist-info/LICENSE
elpigraph_python-0.3.2.dist-info/METADATA
elpigraph_python-0.3.2.dist-info/WHEEL
elpigraph_python-0.3.2.dist-info/desktop.ini
elpigraph_python-0.3.2.dist-info/top_level.txt
elpigraph_python-0.3.2.dist-info/RECORD
