Metadata-Version: 2.1
Name: elpigraph-python
Version: 0.3.2
Summary: UNKNOWN
Home-page: https://github.com/j-bac/elpigraph-python
Maintainer: Jonathan Bac
Maintainer-email: 
License: UNKNOWN
Project-URL: Bug Reports, https://github.com/j-bac/elpigraph-python/issues
Project-URL: Source, https://github.com/j-bac/elpigraph-python/
Keywords: machine_learning graphs dimension_reduction single_cell
Platform: UNKNOWN
Classifier: Development Status :: 3 - Alpha
Classifier: License :: OSI Approved :: GNU General Public License v3 (GPLv3)
License-File: LICENSE
Requires-Dist: numpy >=1.16.2
Requires-Dist: pandas >=0.23.4
Requires-Dist: numba >=0.49.1
Requires-Dist: scikit-learn >=0.21.3
Requires-Dist: scipy >=1.2.0
Requires-Dist: python-igraph >=0.7.1
Requires-Dist: networkx >=2.0
Requires-Dist: matplotlib
Requires-Dist: shapely
Provides-Extra: docs
Requires-Dist: sphinx ; extra == 'docs'
Requires-Dist: sphinx-gallery ; extra == 'docs'
Requires-Dist: sphinx-rtd-theme ; extra == 'docs'
Requires-Dist: numpydoc ; extra == 'docs'
Requires-Dist: matplotlib ; extra == 'docs'
Provides-Extra: tests
Requires-Dist: pytest ; extra == 'tests'
Requires-Dist: pytest-cov ; extra == 'tests'
